RecastPy/__init__.py
RecastPy/misc.py
RecastPy/airflow/__init__.py
RecastPy/airflow/astronomer.py
RecastPy/aws/__init__.py
RecastPy/aws/batch.py
RecastPy/aws/dynamodb.py
RecastPy/aws/iam.py
RecastPy/aws/secrets_manager.py
RecastPy/recast/__init__.py
RecastPy/recast/opman_api.py
RecastPy/recast/opman_db.py
RecastPy/slack/__init__.py
RecastPy/slack/web_client.py
recastpy-0.0.72.dist-info/METADATA
recastpy-0.0.72.dist-info/WHEEL
recastpy-0.0.72.dist-info/top_level.txt
recastpy-0.0.72.dist-info/RECORD
