Metadata-Version: 2.1
Name: recastpy
Version: 0.0.72
Summary: Recast Python Packages
Home-page: https://github.com/getrecast/recast-python-packages
Author: Jeff Carey
Author-email: jeff@getrecast.com
Project-URL: Bug Tracker, https://github.com/getrecast/recast-python-packages/issues
Classifier: Programming Language :: Python :: 3
Classifier: Operating System :: OS Independent
Requires-Python: >=3.8
